MANIFEST.in
README.txt
setup.cfg
setup.py
docs/HISTORY.txt
docs/INSTALL.txt
docs/LICENSE.GPL
docs/LICENSE.txt
googlesitemap/__init__.py
googlesitemap/__init__.pyc
googlesitemap.common.egg-info/PKG-INFO
googlesitemap.common.egg-info/SOURCES.txt
googlesitemap.common.egg-info/dependency_links.txt
googlesitemap.common.egg-info/entry_points.txt
googlesitemap.common.egg-info/namespace_packages.txt
googlesitemap.common.egg-info/not-zip-safe
googlesitemap.common.egg-info/requires.txt
googlesitemap.common.egg-info/top_level.txt
googlesitemap/common/__init__.py
googlesitemap/common/config.py
googlesitemap/common/configure.zcml
googlesitemap/common/interfaces.py
googlesitemap/common/sitemap.py
googlesitemap/common/sitemap.txt
googlesitemap/common/sitemap.xml
googlesitemap/common/sitemapindex.xml
googlesitemap/common/profiles/default/browserlayer.xml
googlesitemap/common/profiles/default/metadata.xml
googlesitemap/common/tests/__init__.py
googlesitemap/common/tests/base.py
googlesitemap/common/tests/test_sitemap.py
googlesitemap/common/tests/test_sitemapindex.py
googlesitemap/common/tests/testing.zcml