Metadata-Version: 1.0
Name: googlesitemap.common
Version: 1.3
Summary: Google Sitemap common support
Home-page: https://github.com/redomino/googlesitemap.common
Author: Davide Moro
Author-email: davide.moro@redomino.com
License: GPL
Keywords: plone google sitemap python
Platform: UNKNOWN
Classifier: Framework :: Plone
Classifier: Programming Language :: Python
Classifier: Topic :: Software Development :: Libraries :: Python Modules
